splink_cluster_studio/__init__.py
splink_cluster_studio/css/custom.css
splink_cluster_studio/graph.py
splink_cluster_studio/jinja/cluster_template.j2
splink_cluster_studio/js_lib/splink_vis_utils.js
splink_cluster_studio/js_lib/vega-embed@6
splink_cluster_studio/js_lib/vega-lite@5
splink_cluster_studio/js_lib/vega@5
splink_cluster_studio/render_template.py
splink_cluster_studio/sql.py
splink_cluster_studio-0.1.1.dist-info/WHEEL
splink_cluster_studio-0.1.1.dist-info/METADATA
splink_cluster_studio-0.1.1.dist-info/RECORD
